qdownloader/__init__.py
qdownloader/__version__.py
qdownloader/guc.py
qdownloader/idm.py
qdownloader/qdownloader.py
qdownloader-1.49.dist-info/METADATA
qdownloader-1.49.dist-info/WHEEL
qdownloader-1.49.dist-info/entry_points.txt
qdownloader-1.49.dist-info/top_level.txt
qdownloader-1.49.dist-info/RECORD
